<usuarios>
  <usuario>
    <rol>cliente</rol>
    <nombre>John</nombre>
    <apellido>Doe</apellido>
    <telefono>123456789</telefono>
    <correo>john.doe@example.com</correo>
    <contrasena>mipassword123</contrasena>
  </usuario>
  <usuario>
    <rol>administrador</rol>
    <nombre>saul</nombre>
    <apellido>perez</apellido>
    <telefono>1562</telefono>
    <correo>saul@gmail.com</correo>
    <contrasena>123</contrasena>
  </usuario>
  <usuario>
    <rol>administrador</rol>
    <nombre>jack</nombre>
    <apellido>martinez</apellido>
    <telefono>jack@gmail.com</telefono>
    <correo>jack@gmail.com</correo>
    <contrasena>12</contrasena>
  </usuario>
  <usuario>
    <rol>administrador</rol>
    <nombre>Jazmin</nombre>
    <apellido>Cital&#225;n</apellido>
    <telefono>59479135</telefono>
    <correo>jazmin@gmail.com</correo>
    <contrasena>arbol</contrasena>
  </usuario>
  <usuario>
    <rol>administrador</rol>
    <nombre>Javier</nombre>
    <apellido>Sanchez</apellido>
    <telefono>59135412</telefono>
    <correo>javier@gmail.com</correo>
    <contrasena>carro</contrasena>
  </usuario>
  <usuario>
    <rol>cliente</rol>
    <nombre>Sebastian</nombre>
    <apellido>Hernandez</apellido>
    <telefono>48236957</telefono>
    <correo>sebas@gmail.com</correo>
    <contrasena>print</contrasena>
  </usuario>
</usuarios>